simple_weather_cli/__init__.py
simple_weather_cli/weather.py
beautiful_weather_cli-0.1.dist-info/METADATA
beautiful_weather_cli-0.1.dist-info/WHEEL
beautiful_weather_cli-0.1.dist-info/entry_points.txt
beautiful_weather_cli-0.1.dist-info/top_level.txt
beautiful_weather_cli-0.1.dist-info/RECORD
